pyqt_openai/__init__.py
pyqt_openai/aboutDialog.py
pyqt_openai/config_loader.py
pyqt_openai/customizeDialog.py
pyqt_openai/doNotAskAgainDialog.py
pyqt_openai/fontWidget.py
pyqt_openai/globals.py
pyqt_openai/icon.ico
pyqt_openai/main.py
pyqt_openai/mainWindow.py
pyqt_openai/models.py
pyqt_openai/shortcutDialog.py
pyqt_openai/sqlite.py
pyqt_openai/updateSoftwareDialog.py
pyqt_openai/ico/add.svg
pyqt_openai/ico/case.svg
pyqt_openai/ico/close.svg
pyqt_openai/ico/copy.svg
pyqt_openai/ico/customize.svg
pyqt_openai/ico/delete.svg
pyqt_openai/ico/discord.svg
pyqt_openai/ico/export.svg
pyqt_openai/ico/favorite_no.svg
pyqt_openai/ico/favorite_yes.svg
pyqt_openai/ico/file.svg
pyqt_openai/ico/focus_mode.svg
pyqt_openai/ico/fullscreen.svg
pyqt_openai/ico/github.svg
pyqt_openai/ico/history.svg
pyqt_openai/ico/import.svg
pyqt_openai/ico/info.svg
pyqt_openai/ico/kofi.png
pyqt_openai/ico/next.svg
pyqt_openai/ico/openai.png
pyqt_openai/ico/openai.svg
pyqt_openai/ico/patreon.svg
pyqt_openai/ico/paypal.png
pyqt_openai/ico/prev.svg
pyqt_openai/ico/prompt.svg
pyqt_openai/ico/question.svg
pyqt_openai/ico/realtime_api.svg
pyqt_openai/ico/record.svg
pyqt_openai/ico/refresh.svg
pyqt_openai/ico/regex.svg
pyqt_openai/ico/save.svg
pyqt_openai/ico/search.svg
pyqt_openai/ico/send.svg
pyqt_openai/ico/setting.svg
pyqt_openai/ico/shortcut.svg
pyqt_openai/ico/sidebar.svg
pyqt_openai/ico/speaker.svg
pyqt_openai/ico/stackontop.svg
pyqt_openai/ico/update.svg
pyqt_openai/ico/user.png
pyqt_openai/ico/user.svg
pyqt_openai/ico/vertical_three_dots.svg
pyqt_openai/ico/word.svg
pyqt_openai/img/import_prompt_with_csv_right_form.png
pyqt_openai/lang/translations.json
pyqt_openai/lang/translations.py
pyqt_openai/prompt_res/alex_brogan.json
pyqt_openai-1.8.3.dist-info/LICENSE
pyqt_openai-1.8.3.dist-info/METADATA
pyqt_openai-1.8.3.dist-info/WHEEL
pyqt_openai-1.8.3.dist-info/entry_points.txt
pyqt_openai-1.8.3.dist-info/top_level.txt
pyqt_openai-1.8.3.dist-info/RECORD
