Metadata-Version: 2.1
Name: pyqt-openai
Version: 1.8.3
Summary: Python multipurpose chatbot that user can use GPT, other AI models altogether (Release Name: VividNode)
Author-email: Jung Gyu Yoon <yjg30737@gmail.com>
License: MIT
Project-URL: homepage, https://github.com/yjg30737/pyqt-openai.git
Keywords: openai,pyqt,pyqt5,pyqt6,pyside6,desktop,app,chatbot,gpt,replicate,gemini,claude,llama,llm,gpt4free,litellm
Classifier: Development Status :: 4 - Beta
Classifier: Intended Audience :: Developers
Classifier: Topic :: Software Development :: Libraries
Classifier: License :: OSI Approved :: MIT License
Classifier: Programming Language :: Python
Classifier: Programming Language :: Python :: 3
Classifier: Programming Language :: Python :: 3.10
Classifier: Programming Language :: Python :: 3.11
Classifier: Programming Language :: Python :: 3.12
Classifier: Topic :: Software Development :: Libraries :: Application Frameworks
Classifier: Topic :: Software Development :: User Interfaces
Requires-Python: <3.13,>=3.10
License-File: LICENSE
Requires-Dist: PySide6
Requires-Dist: pyperclip
Requires-Dist: jinja2
Requires-Dist: requests
Requires-Dist: pyaudio
Requires-Dist: pillow
Requires-Dist: psutil
Requires-Dist: filetype
Requires-Dist: openai
Requires-Dist: anthropic
Requires-Dist: google-generativeai
Requires-Dist: replicate
Requires-Dist: llama-index
Requires-Dist: docx2txt
Requires-Dist: openpyxl
Requires-Dist: g4f==0.3.3.4
Requires-Dist: curl_cffi
Requires-Dist: litellm
Requires-Dist: edge-tts
